mdblog/__init__.py
mdblog/blueprint.py
mdblog/config.py
mdblog/env.py
mdblog/server.py
mdblog/utils.py
mdblog/clitools/__init__.py
mdblog/clitools/cli.py
mdblog/data/config.toml
mdblog/data/demo.md
mdblog/data/mdblog/Dockerfile
mdblog/data/mdblog/build-docker.sh
mdblog/data/mdblog/config.toml
mdblog/data/mdblog/docker-compose.yaml
mdblog/data/static/alertify.min.css
mdblog/data/static/alertify.min.js
mdblog/data/static/bootstrap.min.css
mdblog/data/static/bootstrap.min.js
mdblog/data/static/highlight.min.js
mdblog/data/static/jquery.jgrowl.min.js
mdblog/data/static/jquery.min.js
mdblog/data/static/jsonform.js
mdblog/data/static/jsv.js
mdblog/data/static/marked.min.js
mdblog/data/static/mdview.js
mdblog/data/static/popper.min.js
mdblog/data/static/underscore.js
mdblog/data/static/highlightjs/default.min.css
mdblog/data/static/style/fluent-dark.css
mdblog/data/static/style/fluent.css
mdblog/data/templates/nav.html
mdblog/data/templates/view-folder.html
mdblog/data/templates/view.html
mdblog-0.0.2.7.dist-info/LICENSE
mdblog-0.0.2.7.dist-info/METADATA
mdblog-0.0.2.7.dist-info/WHEEL
mdblog-0.0.2.7.dist-info/entry_points.txt
mdblog-0.0.2.7.dist-info/top_level.txt
mdblog-0.0.2.7.dist-info/RECORD
