Metadata-Version: 2.1
Name: mdblog
Version: 0.0.2.7
Summary: markdown blog server
Home-page: http://github.com/Peiiii/blog.md
Author: Wang Pei
Author-email: 1535376447@qq.com
License: UNKNOWN
Platform: UNKNOWN
Classifier: Programming Language :: Python :: 3
Classifier: License :: OSI Approved :: MIT License
Classifier: Operating System :: OS Independent
Requires-Python: >=3.0
Requires-Dist: sanic
Requires-Dist: jinja2
Requires-Dist: fire
Requires-Dist: toml
